pydbclib/__init__.py
pydbclib/database.py
pydbclib/drivers.py
pydbclib/exceptions.py
pydbclib/record.py
pydbclib/sql.py
pydbclib/utils.py
pydbclib-2.2.3.dist-info/LICENSE
pydbclib-2.2.3.dist-info/METADATA
pydbclib-2.2.3.dist-info/WHEEL
pydbclib-2.2.3.dist-info/top_level.txt
pydbclib-2.2.3.dist-info/zip-safe
pydbclib-2.2.3.dist-info/RECORD
