Metadata-Version: 2.1
Name: pydbclib
Version: 2.2.3
Summary: Python Database Connectivity Lib
Home-page: https://github.com/taogeYT/pydbclib
Author: liyatao
Author-email: li_yatao@outlook.com
License: Apache 2.0
Platform: UNKNOWN
Classifier: Development Status :: 5 - Production/Stable
Classifier: Intended Audience :: Developers
Classifier: License :: OSI Approved :: Apache Software License
Classifier: Programming Language :: Python
Classifier: Programming Language :: Python :: 3.6
Classifier: Programming Language :: Python :: 3.7
Classifier: Programming Language :: Python :: 3.8
Requires-Python: >=3.6
License-File: LICENSE
Requires-Dist: sqlalchemy (<1.4.0,>=1.1.14)
Requires-Dist: sqlparse
Requires-Dist: log4py (>=2.1)
